gomp/__init__.py
gomp/gomp.py
gomp-1.1.1.dist-info/LICENSE.md
gomp-1.1.1.dist-info/METADATA
gomp-1.1.1.dist-info/WHEEL
gomp-1.1.1.dist-info/entry_points.txt
gomp-1.1.1.dist-info/top_level.txt
gomp-1.1.1.dist-info/RECORD
