Metadata-Version: 2.1
Name: gomp
Version: 1.1.1
Summary: Git cOMPare
Home-page: https://www.markforged.com
Author: Markforged
Author-email: software@markforged.com
Classifier: Programming Language :: Python :: 3
Classifier: License :: OSI Approved :: MIT License
Classifier: Operating System :: OS Independent
Requires-Python: >=3
License-File: LICENSE.md
